quick_logger/__init__.py
quick_logger/logger.py
quick_logger/logger_config.py
quick_logger-0.2.0.dist-info/LICENSE
quick_logger-0.2.0.dist-info/METADATA
quick_logger-0.2.0.dist-info/WHEEL
quick_logger-0.2.0.dist-info/RECORD
